<mjloggm ver="2.3"><SHUFFLE seed="mt19937ar-sha512-n288,55B633D3,0ED4F312,851C5D3D,0FBA2A3A,78662E74,B5DD8457,1F6EC346,27AF4E16,A80BEEDB,2B800CD4,6C7AB487,C9FFBAE7,BE1B9E0E,8565AC6D,68FD1039,8497BAB0,ED41E6C5,11C33D18,EE7CE9AF,09A62BC3,EA531B01,FAC1D661,1EB98D22,01A50C39,3D7781BE,5D5C0D21,D5DCC44F,79943354,621D53D2,FF949BD3,38F8799B,49055678" ref=""/><GO type="225"/><UN n0="%E9%9D%92%E5%B1%B1%E5%AD%A6%E9%99%A2%EF%BC%94%E5%B9%B4" n1="%E5%8F%82%E7%B3%BB%E5%A4%A7%E6%9C%AC%E5%96%B6" n2="%E3%81%B3%E3%82%8A%E3%81%B3%E3%82%8A%E2%98%86%E3%83%93%E3%83%AA%E3%83%BC" n3="%E7%AE%A1%E5%AF%9D" dan="17,16,16,16" rate="2072,2131,2148,2117" sx="F,M,M,M"/><TAIKYOKU oya="0"/><INIT seed="0,0,0,5,2,73" ten="250,250,250,250" oya="0" hai0="1,38,124,21,103,86,43,37,18,63,121,61,112" hai1="105,131,19,45,100,9,10,54,49,22,94,123,107" hai2="12,132,71,11,101,72,77,127,42,8,0,87,108" hai3="26,97,29,33,129,110,36,57,74,122,28,125,79"/><T66/><D121/><U111/><E123/><V41/><F71/><W82/><G122/><T17/><D112/><U117/><E117/><V23/><F72/><W88/><G36/><T60/><D1/><U48/><E111/><V13/><F108/><W16/><G110/><T85/><D124/><U84/><E131/><V44/><F127/><W52/><G125/><T65/><D103/><U14/><E49/><V7/><F101/><W106/><G129/><T95/><D43/><U119/><E119/><V135/><F0/><W69/><G69/><T128/><D128/><U115/><E115/><V5/><F23/><W80/><G106/><T91/><D86/><U20/><E20/><V98/><F98/><W25/><G16/><T130/><D130/><U76/><E100/><V58/><F58/><W92/><G80/><T24/><REACH who="0" step="1"/><D18/><REACH who="0" step="2"/><U83/><REACH who="1" step="1"/><E94/><REACH who="1" step="2"/><V30/><F42/><W46/><G46/><T104/><D104/><AGARI ba="0,2" hai="9,10,14,19,22,45,48,54,76,83,84,104,105,107" machi="104" ten="40,5200,0" yaku="1,1,2,1,52,1,53,0" doraHai="73" doraHaiUra="99" who="1" fromWho="0" sc="240,-52,240,72,250,0,250,0" /><INIT seed="1,0,0,3,0,93" ten="188,312,250,250" oya="1" hai0="91,79,123,6,55,18,122,112,56,36,78,48,30" hai1="67,103,21,42,19,10,75,111,57,53,127,134,88" hai2="126,124,26,64,128,76,46,38,28,58,125,61,34" hai3="59,5,109,117,16,135,95,20,51,0,97,3,47"/><U39/><E75/><V8/><F128/><W9/><G109/><T32/><D112/><U33/><E33/><V102/><F76/><W17/><G135/><T73/><D36/><U92/><E134/><V2/><F102/><W101/><G117/><T11/><D18/><U12/><E111/><V84/><F84/><W63/><G0/><T107/><D107/><U114/><E114/><V35/><F35/><W41/><REACH who="3" step="1"/><G20/><REACH who="3" step="2"/><T22/><D32/><U85/><E127/><V31/><F2/><W25/><G25/><T27/><D73/><U113/><E113/><V72/><F26/><W49/><G49/><T133/><D133/><U108/><E108/><V118/><F34/><W60/><G60/><T14/><REACH who="0" step="1"/><D91/><REACH who="0" step="2"/><N who="1" m="53359" /><E39/><V44/><F38/><W100/><G100/><T62/><D62/><U40/><E103/><V94/><F72/><W7/><G7/><T131/><D131/><U4/><E88/><V45/><F118/><W104/><G104/><T83/><D83/><U23/><E4/><V69/><F94/><W90/><G90/><T77/><AGARI ba="0,2" hai="6,11,14,22,27,30,48,55,56,77,78,79,122,123" machi="77" ten="30,2000,0" yaku="1,1,0,1,53,0" doraHai="93" doraHaiUra="71" who="0" fromWho="0" sc="178,40,312,-10,250,-5,240,-5" /><INIT seed="2,0,0,3,4,114" ten="218,302,245,235" oya="2" hai0="45,123,11,131,67,107,62,4,44,98,80,10,94" hai1="39,75,63,102,27,16,79,115,18,106,132,64,33" hai2="9,54,93,22,20,55,38,88,78,32,15,76,58" hai3="41,21,5,121,112,51,124,7,71,57,13,125,74"/><V23/><F32/><W35/><G35/><T103/><D123/><U49/><E115/><V3/><F3/><W101/><G121/><T91/><D131/><U0/><E39/><V81/><F38/><W100/><G71/><T12/><D11/><U105/><E0/><V25/><F25/><W111/><G74/><T17/><D4/><U99/><E106/><V128/><F128/><W24/><G111/><T120/><D120/><U14/><E132/><V84/><F81/><W40/><G112/><T66/><D67/><U31/><E49/><V87/><F84/><W119/><G13/><T73/><D73/><U95/><E95/><V37/><F37/><W52/><G119/><T85/><REACH who="0" step="1"/><D107/><REACH who="0" step="2"/><U72/><E75/><V126/><F126/><N who="3" m="48747" /><G5/><T70/><AGARI ba="0,1" hai="10,12,17,44,45,62,66,70,80,85,91,94,98,103" machi="70" ten="20,2700,0" yaku="1,1,0,1,7,1,53,0" doraHai="114" doraHaiUra="69" who="0" fromWho="0" sc="208,37,302,-7,245,-13,235,-7" /><INIT seed="3,0,0,2,1,22" ten="245,295,232,228" oya="3" hai0="101,84,8,16,11,115,98,106,32,128,27,64,67" hai1="14,79,121,108,97,122,24,88,74,112,102,37,45" hai2="39,34,111,110,49,61,33,68,117,15,124,10,9" hai3="126,3,69,130,59,104,73,129,44,91,6,53,4"/><W47/><G69/><T38/><D38/><U51/><E112/><V26/><F39/><W134/><G134/><T83/><D115/><U133/><E37/><V72/><F72/><W56/><G104/><T5/><D128/><N who="3" m="49257" /><G73/><T96/><D96/><U55/><E133/><V71/><F117/><W94/><G126/><T125/><D125/><U28/><E108/><V119/><F119/><W86/><G59/><T66/><D5/><N who="3" m="2153" /><G3/><T85/><D85/><U118/><E118/><V89/><F124/><W105/><G105/><T43/><D43/><U109/><E109/><V54/><F111/><W70/><G70/><T57/><D57/><U42/><E14/><V81/><F71/><W99/><G86/><T18/><D84/><U20/><E121/><V52/><F68/><W7/><N who="3" m="2161" /><W92/><DORA hai="80" /><G92/><T19/><REACH who="0" step="1"/><D83/><REACH who="0" step="2"/><U40/><E122/><V2/><F81/><W58/><G56/><T48/><D48/><AGARI ba="0,1" hai="44,47,48,53,58,91,94,99" m="2161,49257" machi="48" ten="40,2000,0" yaku="19,1" doraHai="22,80" who="3" fromWho="0" sc="235,-20,295,0,232,0,228,30" /><INIT seed="3,1,0,5,2,24" ten="215,295,232,258" oya="3" hai0="66,127,67,106,63,39,82,133,128,115,96,1,7" hai1="130,107,64,54,129,81,32,53,97,86,110,55,93" hai2="78,95,26,29,14,43,0,116,6,56,50,108,72" hai3="119,76,28,70,89,122,62,98,135,105,40,23,51"/><W88/><G122/><T69/><D67/><U85/><E32/><V31/><F0/><W11/><G119/><T123/><D123/><U8/><E107/><V75/><F116/><W21/><G105/><T30/><D115/><U18/><E64/><V103/><F75/><W61/><G70/><T112/><D112/><U38/><E38/><V90/><F103/><W12/><G76/><T109/><D109/><U111/><E8/><N who="2" m="4375" /><F78/><W134/><G40/><T94/><D106/><U35/><E35/><V124/><F72/><W2/><G51/><T47/><D127/><U68/><E18/><V120/><F108/><N who="1" m="41513" /><E68/><V80/><F124/><W83/><G21/><T33/><D128/><N who="1" m="49259" /><E81/><V41/><F80/><W44/><G83/><T91/><D133/><U52/><N who="1" m="13824" /><DORA hai="100" /><U42/><E42/><V10/><F43/><W57/><G11/><T131/><D131/><U22/><E22/><V71/><F10/><W15/><G23/><T65/><D82/><U20/><E20/><N who="2" m="15559" /><F71/><W125/><G125/><T13/><D66/><U34/><E34/><V59/><F120/><W117/><G134/><T102/><D33/><U74/><E74/><V9/><F9/><W37/><G135/><T16/><D30/><U79/><E79/><V114/><F31/><W99/><G28/><T126/><D126/><U25/><E25/><V113/><F114/><W19/><G117/><T60/><D60/><U45/><E45/><N who="2" m="25903" /><F113/><W49/><G61/><T27/><D27/><U48/><E48/><V5/><F5/><W4/><G62/><T73/><D16/><U104/><E104/><V77/><F77/><RYUUKYOKU ba="1,0" sc="215,-15,295,15,232,15,258,-15" hai1="85,86,93,97" hai2="56,59,90,95" owari="200,-30,310,41,247,5,243,-16" /></mjloggm>