<mjloggm ver="2.3"><SHUFFLE seed="mt19937ar-sha512-n288,39477398,3DDBC306,8EC3BAEC,7FFD2E13,C207C313,58BD53C7,9FBDA850,78DC212E,1FCDC48B,9B79C4A6,CBB76803,3EA50BF7,341D4BD9,288F0787,2BF34A43,364DBE93,D0C37061,60E6AC5D,C53F5FE9,05C6658B,4A20EE96,E5B76FAD,B573044C,8455FB21,DD3D7B2E,7C1AC016,2A8178CB,DE787E00,C454465C,B629A532,C9B69F1F,35C9E991" ref=""/><GO type="225"/><UN n0="%E7%AE%A1%E5%AF%9D" n1="%E8%88%9E%E3%81%84%E9%99%8D%E3%82%8A%E3%81%9F%E8%BD%9F" n2="%E3%82%AA%E3%82%AB%E3%83%AB%EF%BD%94" n3="%E9%9D%92%E5%B1%B1%E5%AD%A6%E9%99%A2%EF%BC%94%E5%B9%B4" dan="16,17,16,17" rate="2122,2064,2084,2058" sx="M,M,M,F"/><TAIKYOKU oya="0"/><INIT seed="0,0,0,1,1,51" ten="250,250,250,250" oya="0" hai0="21,110,69,29,2,49,99,11,111,6,92,39,36" hai1="122,48,109,63,112,96,88,121,84,67,16,19,76" hai2="56,134,104,77,62,105,97,58,78,55,103,68,44" hai3="101,81,71,127,83,34,50,7,43,125,46,91,31"/><T80/><D69/><U75/><E75/><V23/><F105/><W113/><G71/><T117/><D117/><U4/><E4/><V0/><F0/><W1/><G113/><T100/><D80/><U41/><E112/><V12/><F134/><W17/><G17/><T86/><D86/><U79/><E109/><N who="0" m="41481" /><D29/><U114/><E114/><V108/><F68/><W116/><G116/><T3/><D3/><U14/><E41/><V73/><F73/><W28/><G28/><T33/><D33/><U57/><E48/><V30/><F108/><W82/><G31/><T89/><D21/><U98/><E19/><V53/><F44/><W52/><G34/><T5/><D5/><U70/><E70/><V130/><F130/><W37/><G7/><T38/><D49/><U8/><E98/><V131/><F131/><W135/><G1/><T87/><D87/><U61/><E61/><V24/><F12/><W15/><G15/><T129/><D129/><U13/><E13/><V126/><F126/><N who="3" m="48139" /><G135/><T74/><D74/><U25/><E25/><V119/><F119/><W120/><G120/><T54/><D100/><U20/><E8/><V93/><F104/><W85/><G101/><T95/><D95/><N who="1" m="56423" /><E121/><V72/><F72/><W107/><G107/><T35/><D35/><U106/><E106/><V64/><F64/><W128/><G128/><T27/><D27/><U102/><E122/><V9/><F9/><W18/><G18/><T123/><D123/><U133/><E102/><V60/><AGARI ba="0,0" hai="23,24,30,53,55,56,58,60,62,77,78,93,97,103" machi="60" ten="20,12000,2" yaku="0,1,7,1,9,1,8,1,52,2" doraHai="51" who="2" fromWho="2" sc="250,-60,250,-30,250,120,250,-30" /><INIT seed="1,0,0,0,2,103" ten="190,220,370,220" oya="1" hai0="3,115,45,107,124,39,38,20,114,100,63,133,97" hai1="42,54,69,89,79,34,68,128,7,108,57,123,47" hai2="72,35,92,90,27,43,28,48,112,88,2,106,11" hai3="121,50,36,87,75,17,49,102,6,73,105,44,131"/><U81/><E123/><V46/><F72/><W55/><G121/><T61/><D133/><U110/><E34/><V96/><F112/><W15/><G36/><T12/><D3/><U10/><E89/><V67/><F67/><W37/><G37/><T119/><D38/><N who="1" m="21975" /><E57/><V65/><F65/><W101/><G6/><T33/><D119/><U74/><E54/><V104/><REACH who="2" step="1"/><F90/><REACH who="2" step="2"/><W21/><G75/><T134/><D114/><U40/><E128/><V86/><F86/><W31/><G73/><T85/><D115/><U130/><E130/><V82/><F82/><W53/><G131/><T29/><D85/><U14/><E81/><V83/><F83/><W60/><G87/><T93/><D134/><U5/><E74/><V13/><F13/><W80/><G80/><T76/><D12/><U64/><E64/><V52/><F52/><W8/><G55/><T70/><D76/><U113/><E79/><V126/><F126/><W19/><G53/><T32/><D124/><U0/><E113/><V62/><F62/><W58/><G60/><T66/><D61/><U59/><E40/><V135/><F135/><W125/><G125/><T23/><D63/><U95/><E14/><V109/><F109/><W41/><G41/><N who="0" m="22719" /><D66/><U122/><E108/><V16/><F16/><W25/><G19/><T117/><D117/><U1/><E110/><V111/><F111/><W56/><G17/><T18/><D18/><U77/><E77/><V116/><F116/><W26/><G15/><T4/><D4/><AGARI ba="0,1" hai="2,4,11,27,28,35,43,46,48,88,92,96,104,106" machi="4" ten="40,8000,1" yaku="1,1,52,2,54,1,53,1" doraHai="103" doraHaiUra="24" who="2" fromWho="0" sc="190,-80,220,0,360,90,220,0" /><INIT seed="2,0,0,3,1,7" ten="110,220,450,220" oya="2" hai0="73,54,104,116,92,77,27,103,45,100,30,19,15" hai1="121,126,61,63,110,115,10,72,64,44,127,49,133" hai2="79,43,102,31,21,16,78,94,87,40,33,34,91" hai3="50,69,90,107,8,29,32,106,24,125,120,41,93"/><V75/><F102/><W83/><G120/><T37/><D116/><U85/><E72/><V22/><F33/><W66/><G83/><T99/><D73/><U42/><E121/><V12/><F34/><W18/><G125/><N who="1" m="47626" /><E115/><V96/><F75/><W53/><G41/><N who="2" m="15945" /><F96/><W25/><G66/><T111/><D111/><U98/><E98/><V89/><F91/><W70/><G107/><T134/><D134/><U130/><E110/><V36/><F36/><W38/><G38/><T76/><D37/><U95/><E130/><V5/><F5/><W39/><G39/><T1/><D1/><U124/><E124/><V97/><F97/><W101/><G106/><T82/><D82/><U114/><E114/><V67/><F67/><W119/><G101/><T9/><D100/><U62/><E64/><V129/><F129/><W55/><G32/><T11/><D104/><U80/><E95/><V112/><F112/><W13/><G93/><T28/><D9/><U60/><E10/><N who="2" m="6167" /><F31/><N who="0" m="11818" /><D27/><U0/><E0/><V6/><F6/><W132/><G25/><T51/><AGARI ba="0,0" hai="11,15,19,45,51,54,76,77,92,99,103" m="11818" machi="51" ten="30,2000,0" yaku="8,1,52,1" doraHai="7" who="0" fromWho="0" sc="110,20,220,-5,450,-10,220,-5" /><INIT seed="3,0,0,3,3,7" ten="130,215,440,215" oya="3" hai0="109,58,123,68,115,33,88,119,4,13,101,42,74" hai1="63,62,105,57,56,39,107,95,71,49,133,59,24" hai2="64,112,85,87,5,102,14,114,99,3,22,90,124" hai3="132,32,23,48,11,106,80,15,100,28,31,116,98"/><W128/><G116/><T37/><D123/><U1/><E1/><V81/><F3/><W30/><G32/><T25/><D119/><U94/><E39/><V104/><F124/><W76/><G128/><T10/><D68/><U34/><E49/><V97/><F97/><W29/><G29/><T130/><D109/><U65/><E62/><V84/><F84/><W19/><G132/><T118/><D118/><U38/><E38/><V131/><F131/><W77/><G80/><T129/><D115/><U0/><E0/><V82/><F64/><W70/><G70/><T69/><D69/><U43/><E43/><V51/><F51/><W36/><G36/><T96/><D74/><U41/><E41/><V20/><F22/><W110/><G110/><T91/><D129/><U103/><E133/><V26/><F14/><W126/><G126/><T45/><D130/><U117/><E117/><V73/><F5/><W53/><REACH who="3" step="1"/><G23/><REACH who="3" step="2"/><T86/><D58/><AGARI ba="0,1" hai="11,15,19,28,30,31,48,53,58,76,77,98,100,106" machi="58" ten="40,7700,0" yaku="1,1,2,1,52,1,53,0" doraHai="7" doraHaiUra="61" who="3" fromWho="0" sc="130,-77,215,0,440,0,205,87" /><INIT seed="3,1,0,2,4,39" ten="53,215,440,292" oya="3" hai0="3,60,23,94,0,126,58,55,119,97,51,93,48" hai1="109,33,66,131,65,105,120,118,124,114,115,35,84" hai2="91,102,22,62,101,38,82,107,1,7,10,129,50" hai3="29,46,40,130,113,12,135,15,92,21,42,14,89"/><W41/><G113/><N who="1" m="43018" /><E84/><V95/><F38/><W110/><G130/><T70/><D119/><U44/><E105/><V76/><F129/><W116/><G116/><T27/><D126/><U112/><E112/><V56/><F107/><W9/><G135/><T86/><D70/><U18/><E18/><V20/><F50/><N who="3" m="26951" /><G110/><T69/><D69/><U68/><E68/><V34/><F34/><W74/><G74/><T2/><D86/><U78/><E78/><V43/><F43/><N who="3" m="16395" /><G9/><T57/><D93/><U6/><E109/><V98/><F102/><W32/><G32/><T133/><D133/><U11/><E35/><V45/><F101/><W8/><G8/><T121/><D121/><U96/><E11/><V85/><F45/><W132/><G132/><T108/><D108/><U73/><E44/><V47/><F47/><W99/><G29/><T5/><D5/><U111/><E6/><V13/><F1/><W49/><G49/><T28/><D48/><U67/><E73/><V125/><REACH who="2" step="1"/><F125/><REACH who="2" step="2"/><W77/><G77/><T122/><D122/><U52/><E33/><V106/><F106/><W83/><G83/><T123/><D123/><U54/><E124/><V127/><F127/><W4/><G4/><T72/><D72/><U31/><E120/><V59/><F59/><W103/><G103/><T64/><REACH who="0" step="1"/><D0/><REACH who="0" step="2"/><U36/><E118/><V19/><F19/><AGARI ba="1,2" hai="12,14,15,19,21,89,92,99" m="16395,26951" machi="19" ten="30,12000,1" yaku="8,1,52,4" doraHai="39" who="3" fromWho="2" sc="43,0,215,0,430,-123,292,143" owari="43,-46,215,-18,307,11,435,53" /></mjloggm>